htty_core-0.2.30.data/scripts/ht
htty_core-0.2.30.dist-info/METADATA
htty_core-0.2.30.dist-info/WHEEL
htty_core-0.2.30.dist-info/licenses/LICENSE
htty_core/__init__.py
htty_core/constants.py
htty_core/core.py
htty_core/py.typed
htty_core-0.2.30.dist-info/RECORD
