Metadata-Version: 2.4
Name: htty_core
Version: 0.2.30
Classifier: Development Status :: 4 - Beta
Classifier: Environment :: Console
Classifier: Intended Audience :: Developers
Classifier: License :: OSI Approved :: MIT License
Classifier: Operating System :: OS Independent
Classifier: Programming Language :: Rust
Classifier: Topic :: Software Development :: Testing
Classifier: Topic :: Software Development :: Libraries
Classifier: Topic :: System :: Shells
Classifier: Topic :: Terminals
License-File: LICENSE
Summary: Headless Terminal - Rust binary for terminal automation
Keywords: terminal,automation,pty,headless,subprocess
Home-Page: https://github.com/MatrixManAtYrService/ht
Author-email: Matt Rixman <MatrixManAtYrService@users.noreply.github.com>
License: MIT
Requires-Python: >=3.10
Project-URL: Homepage, https://github.com/MatrixManAtYrService/ht
Project-URL: Documentation, https://github.com/MatrixManAtYrService/ht
Project-URL: Repository, https://github.com/MatrixManAtYrService/ht
Project-URL: Issues, https://github.com/MatrixManAtYrService/ht/issues
